{"URL":"https://www.instagram.com/paweensuda/","Name":"paweensuda","FollowerCount":30647,"FollowingCount":377,"Followings":[{"Name":"saritapha","URL":"https://www.instagram.com/saritapha/"},{"Name":"earth_je","URL":"https://www.instagram.com/earth_je/"},{"Name":"raftnan","URL":"https://www.instagram.com/raftnan/"},{"Name":"amway_jidapa4289","URL":"https://www.instagram.com/amway_jidapa4289/"},{"Name":"paweeniverse","URL":"https://www.instagram.com/paweeniverse/"},{"Name":"clintbondad","URL":"https://www.instagram.com/clintbondad/"},{"Name":"officialeilalopes","URL":"https://www.instagram.com/officialeilalopes/"},{"Name":"chakclub_makeup","URL":"https://www.instagram.com/chakclub_makeup/"},{"Name":"iyada__ice","URL":"https://www.instagram.com/iyada__ice/"},{"Name":"unhcr.thailand","URL":"https://www.instagram.com/unhcr.thailand/"},{"Name":"balletphotographymanila","URL":"https://www.instagram.com/balletphotographymanila/"},{"Name":"menemonn","URL":"https://www.instagram.com/menemonn/"},{"Name":"sabinameisinger","URL":"https://www.instagram.com/sabinameisinger/"},{"Name":"analilianaaviao","URL":"https://www.instagram.com/analilianaaviao/"},{"Name":"kiara.lizpr","URL":"https://www.instagram.com/kiara.lizpr/"},{"Name":"jongsuk0206","URL":"https://www.instagram.com/jongsuk0206/"},{"Name":"jareeluck","URL":"https://www.instagram.com/jareeluck/"},{"Name":"arm__atcha","URL":"https://www.instagram.com/arm__atcha/"},{"Name":"saragavranic","URL":"https://www.instagram.com/saragavranic/"},{"Name":"chjosa","URL":"https://www.instagram.com/chjosa/"},{"Name":"nnunstn","URL":"https://www.instagram.com/nnunstn/"},{"Name":"chutikan_cw","URL":"https://www.instagram.com/chutikan_cw/"},{"Name":"nichapanuiw","URL":"https://www.instagram.com/nichapanuiw/"},{"Name":"khunanya_chom","URL":"https://www.instagram.com/khunanya_chom/"},{"Name":"violettewautier","URL":"https://www.instagram.com/violettewautier/"},{"Name":"natharuetai.a","URL":"https://www.instagram.com/natharuetai.a/"},{"Name":"nicolene.pb","URL":"https://www.instagram.com/nicolene.pb/"},{"Name":"vatanika_official","URL":"https://www.instagram.com/vatanika_official/"},{"Name":"princejuliocesar","URL":"https://www.instagram.com/princejuliocesar/"},{"Name":"venapraveenar","URL":"https://www.instagram.com/venapraveenar/"},{"Name":"baifaii_sunisa","URL":"https://www.instagram.com/baifaii_sunisa/"},{"Name":"nokphrima","URL":"https://www.instagram.com/nokphrima/"},{"Name":"brothers.page","URL":"https://www.instagram.com/brothers.page/"},{"Name":"kendalljenner","URL":"https://www.instagram.com/kendalljenner/"},{"Name":"dr.pimkhwan","URL":"https://www.instagram.com/dr.pimkhwan/"},{"Name":"jansich","URL":"https://www.instagram.com/jansich/"},{"Name":"ntymisa","URL":"https://www.instagram.com/ntymisa/"},{"Name":"myniname0534","URL":"https://www.instagram.com/myniname0534/"},{"Name":"__esme_","URL":"https://www.instagram.com/__esme_/"},{"Name":"ji.lozan","URL":"https://www.instagram.com/ji.lozan/"},{"Name":"krungor","URL":"https://www.instagram.com/krungor/"},{"Name":"filmany","URL":"https://www.instagram.com/filmany/"},{"Name":"valentinaploy","URL":"https://www.instagram.com/valentinaploy/"},{"Name":"giift_natrapat","URL":"https://www.instagram.com/giift_natrapat/"},{"Name":"pawasutakul","URL":"https://www.instagram.com/pawasutakul/"},{"Name":"sawsing_sorsopit","URL":"https://www.instagram.com/sawsing_sorsopit/"},{"Name":"niinewn3","URL":"https://www.instagram.com/niinewn3/"},{"Name":"chavikax","URL":"https://www.instagram.com/chavikax/"}],"Followers":[],"Posts":[]}